[
  {
    "bbb_achieve_id": "ACH_ISLAND_2",
    "google_achieve_id": "CgkIvZ_r2qUBEAIQCg"
  },
  {
    "bbb_achieve_id": "ACH_ALL_MONSTERS_ISLAND_1",
    "google_achieve_id": "CgkIvZ_r2qUBEAIQCQ"
  },
  {
    "bbb_achieve_id": "ACH_NO_OBSTACLES",
    "google_achieve_id": "CgkIvZ_r2qUBEAIQCA"
  },
  {
    "bbb_achieve_id": "ACH_4_GENE_MONSTER",
    "google_achieve_id": "CgkIvZ_r2qUBEAIQBw"
  },
  {
    "bbb_achieve_id": "ACH_3_GENE_MONSTER",
    "google_achieve_id": "CgkIvZ_r2qUBEAIQBg"
  },
  {
    "bbb_achieve_id": "ACH_MONSTER_LEVEL_15",
    "google_achieve_id": "CgkIvZ_r2qUBEAIQBQ"
  },
  {
    "bbb_achieve_id": "ACH_REACH_LEVEL_10",
    "google_achieve_id": "CgkIvZ_r2qUBEAIQBA"
  },
  {
    "bbb_achieve_id": "ACH_100_HAPPINESS",
    "google_achieve_id": "CgkIvZ_r2qUBEAIQAw"
  },
  {
    "bbb_achieve_id": "ACH_ALL_MONSTERS_ISLAND_2",
    "google_achieve_id": "CgkIvZ_r2qUBEAIQCw"
  },
  {
    "bbb_achieve_id": "ACH_ISLAND_3",
    "google_achieve_id": "CgkIvZ_r2qUBEAIQDA"
  },
  {
    "bbb_achieve_id": "ACH_ALL_MONSTERS_ISLAND_3",
    "google_achieve_id": "CgkIvZ_r2qUBEAIQDQ"
  },
  {
    "bbb_achieve_id": "ACH_ALL_MONSTERS_ISLAND_5",
    "google_achieve_id": "CgkIvZ_r2qUBEAIQEQ"
  },
  {
    "bbb_achieve_id": "ACH_ISLAND_5",
    "google_achieve_id": "CgkIvZ_r2qUBEAIQEA"
  },
  {
    "bbb_achieve_id": "ACH_ALL_MONSTERS_ISLAND_4",
    "google_achieve_id": "CgkIvZ_r2qUBEAIQDw"
  },
  {
    "bbb_achieve_id": "ACH_ISLAND_4",
    "google_achieve_id": "CgkIvZ_r2qUBEAIQDg"
  },
  {
    "bbb_achieve_id": "ACH_BREED_MONSTERS",
    "google_achieve_id": "CgkIvZ_r2qUBEAIQAg"
  },
  {
    "bbb_achieve_id": "ACH_FIRST_MONSTER",
    "google_achieve_id": "CgkIvZ_r2qUBEAIQAQ"
  }
]
